fastaparser/__init__.py
fastaparser/constants.py
fastaparser/fastasequence.py
fastaparser/lettercode.py
fastaparser/parsedefinitionline.py
fastaparser/reader.py
fastaparser/writer.py
fastaparser-1.1.1.dist-info/LICENSE
fastaparser-1.1.1.dist-info/METADATA
fastaparser-1.1.1.dist-info/WHEEL
fastaparser-1.1.1.dist-info/top_level.txt
fastaparser-1.1.1.dist-info/RECORD
