Metadata-Version: 2.1
Name: fastaparser
Version: 1.1.1
Summary: A Python FASTA file Parser and Writer.
Home-page: https://github.com/Kronopt/FastaParser
Author: Pedro HC David, https://github.com/Kronopt
License: GPLv3
Project-URL: Documentation, https://fastaparser.readthedocs.io/en/latest/
Keywords: fasta parser fasta-parser fasta-writer
Classifier: Development Status :: 5 - Production/Stable
Classifier: Intended Audience :: Developers
Classifier: License :: OSI Approved :: GNU General Public License v3 (GPLv3)
Classifier: Natural Language :: English
Classifier: Programming Language :: Python :: 3
Classifier: Programming Language :: Python :: 3.5
Classifier: Programming Language :: Python :: 3.6
Classifier: Programming Language :: Python :: 3.7
Classifier: Programming Language :: Python :: 3.8
Classifier: Programming Language :: Python :: 3.9
Classifier: Programming Language :: Python :: 3.10
License-File: LICENSE
